imy/__init__.py
imy/_task_group.py
imy/assets.py
imy/async_utils.py
imy/deprecations.py
imy/inject.py
imy/logs.py
imy/docstrings/__init__.py
imy/docstrings/data_models.py
imy/docstrings/parsers.py
imy/docstrings/utilities.py
imy-0.7.0.post1.dist-info/METADATA
imy-0.7.0.post1.dist-info/WHEEL
imy-0.7.0.post1.dist-info/licenses/LICENSE
imy-0.7.0.post1.dist-info/RECORD
